LICENSE
MANIFEST.in
README.rst
requirements.txt
setup.cfg
setup.py
test-requirements.txt
sprockets/__init__.py
sprockets.clients.statsd.egg-info/PKG-INFO
sprockets.clients.statsd.egg-info/SOURCES.txt
sprockets.clients.statsd.egg-info/dependency_links.txt
sprockets.clients.statsd.egg-info/namespace_packages.txt
sprockets.clients.statsd.egg-info/not-zip-safe
sprockets.clients.statsd.egg-info/requires.txt
sprockets.clients.statsd.egg-info/top_level.txt
sprockets/clients/__init__.py
sprockets/clients/statsd/__init__.py