Metadata-Version: 1.1
Name: sprockets.clients.statsd
Version: 1.2.1
Summary: A minimalistic statsd client used by sprockets.mixins.statsd
Home-page: https://github.com/sprockets/sprockets.clients.statsd.git
Author: AWeber Communications
Author-email: api@aweber.com
License: Copyright (c) 2014 AWeber Communications
